<?xml version="1.0" encoding="UTF-8" standalone="no"?>
<?OntoDPSData docID="980952" markupID="31259" OntoTechnologyVersion="3.6.9.0"?>
<rdf:RDF xmlns:rdf="http://www.w3.org/1999/02/22-rdf-syntax-ns#" xmlns:Aux="http://www.abbyy.com/ns/Aux#" xmlns:rdfs="http://www.w3.org/2000/01/rdf-schema#" xmlns:RomipAnaphora="http://www.abbyy.com/ns/RomipAnaphora#" xmlns:Basic="http://www.abbyy.com/ns/Basic#">
	<RomipAnaphora:RomipThing rdf:nodeID="bnode8013C8C1-0E0B-462B-9093-147872C61CA1">
		<Basic:identifier xml:lang="ru-RU">нации</Basic:identifier>
		<rdfs:label xml:lang="ru-RU">нация</rdfs:label>
	</RomipAnaphora:RomipThing>
	<RomipAnaphora:RomipThing rdf:nodeID="bnodeBF82A494-7850-4B24-8AA2-620A2169488B">
		<Basic:identifier xml:lang="ru-RU">лидера нации</Basic:identifier>
		<rdfs:label xml:lang="ru-RU">лидера нации</rdfs:label>
	</RomipAnaphora:RomipThing>
	<RomipAnaphora:RomipThing rdf:nodeID="bnode09738B4F-ADE4-49C2-BA51-D3A7269BBCEE">
		<Basic:identifier xml:lang="ru-RU">Назарбаев</Basic:identifier>
		<rdfs:label xml:lang="ru-RU">Назарбаев</rdfs:label>
	</RomipAnaphora:RomipThing>
	<RomipAnaphora:RomipThing rdf:nodeID="bnodeCDC15646-625F-4EA5-BE6E-AD6CF7BE3974">
		<Basic:identifier xml:lang="ru-RU">областных администраций</Basic:identifier>
		<rdfs:label xml:lang="ru-RU">областные администрации</rdfs:label>
	</RomipAnaphora:RomipThing>
	<RomipAnaphora:RomipThing rdf:nodeID="bnodeA09E889E-D93C-450F-83EF-4C79AB2EAC7E">
		<Basic:identifier xml:lang="ru-RU">главам областных администраций</Basic:identifier>
		<rdfs:label xml:lang="ru-RU">главам областных администраций</rdfs:label>
	</RomipAnaphora:RomipThing>
	<RomipAnaphora:RomipThing rdf:nodeID="bnode2194FE51-C170-4203-995D-B21C671DC302">
		<Basic:identifier xml:lang="ru-RU">Нурсултан</Basic:identifier>
		<rdfs:label xml:lang="ru-RU">Нурсултан</rdfs:label>
	</RomipAnaphora:RomipThing>
	<RomipAnaphora:RomipThing rdf:nodeID="bnodeE2368B56-F465-464C-B42C-886CA329AB59">
		<Basic:identifier xml:lang="ru-RU">Астаны</Basic:identifier>
		<rdfs:label xml:lang="ru-RU">Астана</rdfs:label>
	</RomipAnaphora:RomipThing>
	<RomipAnaphora:RomipThing rdf:nodeID="bnode2D82EB63-41C4-4449-9F12-0DCAA1B8D438">
		<Basic:identifier xml:lang="ru-RU">республики</Basic:identifier>
		<rdfs:label xml:lang="ru-RU">республика</rdfs:label>
	</RomipAnaphora:RomipThing>
	<RomipAnaphora:RomipThing rdf:nodeID="bnode3E51FCCF-B1D6-4A6C-8276-5DF37022E63D">
		<Basic:identifier xml:lang="ru-RU">столицу республики</Basic:identifier>
		<rdfs:label xml:lang="ru-RU">столицу республики</rdfs:label>
	</RomipAnaphora:RomipThing>
	<RomipAnaphora:RomipThing rdf:nodeID="bnode7E88EC26-CC6E-4ED8-9804-677F33703875">
		<Basic:identifier xml:lang="ru-RU">он</Basic:identifier>
		<rdfs:label xml:lang="ru-RU">он</rdfs:label>
	</RomipAnaphora:RomipThing>
	<RomipAnaphora:RomipThing rdf:nodeID="bnode0E9EFDAE-9A8E-466D-866F-7AB0FDB53B6B">
		<Basic:identifier xml:lang="ru-RU">своих</Basic:identifier>
		<rdfs:label xml:lang="ru-RU">своих</rdfs:label>
	</RomipAnaphora:RomipThing>
	<RomipAnaphora:RomipThing rdf:nodeID="bnode2735B2C1-6616-49ED-8D8E-64EE9C466FB0">
		<Basic:identifier xml:lang="ru-RU">Казахстана</Basic:identifier>
		<rdfs:label xml:lang="ru-RU">Казахстана</rdfs:label>
	</RomipAnaphora:RomipThing>
	<RomipAnaphora:RomipThing rdf:nodeID="bnodeD6888080-376A-4332-97C1-D261EDA2A4CB">
		<Basic:identifier xml:lang="ru-RU">глава Казахстана</Basic:identifier>
		<rdfs:label xml:lang="ru-RU">глава Казахстана</rdfs:label>
	</RomipAnaphora:RomipThing>
	<RomipAnaphora:RomipThing rdf:nodeID="bnode311CE25D-0485-45A7-A9A5-F1E552F9F3AF">
		<Basic:identifier xml:lang="ru-RU">нации</Basic:identifier>
		<rdfs:label xml:lang="ru-RU">нация</rdfs:label>
	</RomipAnaphora:RomipThing>
	<RomipAnaphora:RomipThing rdf:nodeID="bnode0468F3AE-6E8E-4AD1-A6C7-DF0C9A1BED62">
		<Basic:identifier xml:lang="ru-RU">лидера нации</Basic:identifier>
		<rdfs:label xml:lang="ru-RU">лидера нации</rdfs:label>
	</RomipAnaphora:RomipThing>
	<RomipAnaphora:RomipThing rdf:nodeID="bnode5198DCC8-13C8-43AF-ACEB-ACDBE219947A">
		<Basic:identifier xml:lang="ru-RU">Казахстана</Basic:identifier>
		<rdfs:label xml:lang="ru-RU">Казахстана</rdfs:label>
	</RomipAnaphora:RomipThing>
	<RomipAnaphora:RomipThing rdf:nodeID="bnodeCC167A94-8101-459B-B099-933EA51669EF">
		<Basic:identifier xml:lang="ru-RU">первого президента Казахстана</Basic:identifier>
		<rdfs:label xml:lang="ru-RU">первого президента Казахстана</rdfs:label>
	</RomipAnaphora:RomipThing>
	<RomipAnaphora:RomipThing rdf:nodeID="bnodeE007CBE7-0346-4812-B7C1-9C9F2FC5914C">
		<Basic:identifier xml:lang="ru-RU">своего</Basic:identifier>
		<rdfs:label xml:lang="ru-RU">своего</rdfs:label>
	</RomipAnaphora:RomipThing>
	<RomipAnaphora:RomipThing rdf:nodeID="bnodeB157B53B-5E70-4E32-9F42-81991F9C56AA">
		<Basic:identifier xml:lang="ru-RU">их</Basic:identifier>
		<rdfs:label xml:lang="ru-RU">их</rdfs:label>
	</RomipAnaphora:RomipThing>
	<RomipAnaphora:RomipThing rdf:nodeID="bnodeBFD76367-390B-4EB1-BBAD-174E317B930D">
		<Basic:identifier xml:lang="ru-RU">президента</Basic:identifier>
		<rdfs:label xml:lang="ru-RU">президента</rdfs:label>
	</RomipAnaphora:RomipThing>
	<RomipAnaphora:RomipThing rdf:nodeID="bnode0F3ED7E7-DBF9-4152-8619-C5E3C3731FBC">
		<Basic:identifier xml:lang="ru-RU">им</Basic:identifier>
		<rdfs:label xml:lang="ru-RU">им</rdfs:label>
	</RomipAnaphora:RomipThing>
	<RomipAnaphora:RomipThing rdf:nodeID="bnodeB00EDC9B-071F-4112-B168-70F077F04474">
		<Basic:identifier xml:lang="ru-RU">нации</Basic:identifier>
		<rdfs:label xml:lang="ru-RU">нация</rdfs:label>
	</RomipAnaphora:RomipThing>
	<RomipAnaphora:RomipThing rdf:nodeID="bnodeE23BC4EF-79EF-4973-BD76-53E531A5C503">
		<Basic:identifier xml:lang="ru-RU">лидера нации</Basic:identifier>
		<rdfs:label xml:lang="ru-RU">лидера нации</rdfs:label>
	</RomipAnaphora:RomipThing>
	<RomipAnaphora:RomipThing rdf:nodeID="bnodeB94AA13C-8F0C-4AEA-BC9D-15039287EDAC">
		<Basic:identifier xml:lang="ru-RU">Тот же документ</Basic:identifier>
		<rdfs:label xml:lang="ru-RU">Тот же документ</rdfs:label>
	</RomipAnaphora:RomipThing>
	<RomipAnaphora:RomipThing rdf:nodeID="bnode796B7D55-5DBA-471B-BB96-F23320C70003">
		<Basic:identifier xml:lang="ru-RU">Назарбаева</Basic:identifier>
		<rdfs:label xml:lang="ru-RU">Назарбаева</rdfs:label>
	</RomipAnaphora:RomipThing>
	<RomipAnaphora:RomipThing rdf:nodeID="bnode9A947B7D-851C-485C-BD73-FB175ECF25CC">
		<Basic:identifier xml:lang="ru-RU">его</Basic:identifier>
		<rdfs:label xml:lang="ru-RU">его</rdfs:label>
	</RomipAnaphora:RomipThing>
	<RomipAnaphora:RomipThing rdf:nodeID="bnode2071B14B-B3E2-497A-BE80-8F30034A1A8E">
		<Basic:identifier xml:lang="ru-RU">его</Basic:identifier>
		<rdfs:label xml:lang="ru-RU">его</rdfs:label>
	</RomipAnaphora:RomipThing>
	<RomipAnaphora:RomipThing rdf:nodeID="bnode4E9539B9-42A5-4085-9236-E1149E729E7F">
		<Basic:identifier xml:lang="ru-RU">нации</Basic:identifier>
		<rdfs:label xml:lang="ru-RU">нация</rdfs:label>
	</RomipAnaphora:RomipThing>
	<RomipAnaphora:RomipThing rdf:nodeID="bnodeA4ADA898-B244-45B5-89EC-9028ADFD339C">
		<Basic:identifier xml:lang="ru-RU">лидера нации</Basic:identifier>
		<rdfs:label xml:lang="ru-RU">лидера нации</rdfs:label>
	</RomipAnaphora:RomipThing>
	<RomipAnaphora:RomipThing rdf:nodeID="bnode6C1A3B95-9051-44D7-ABD1-544B6420898E">
		<Basic:identifier xml:lang="ru-RU">нации</Basic:identifier>
		<rdfs:label xml:lang="ru-RU">нация</rdfs:label>
	</RomipAnaphora:RomipThing>
	<RomipAnaphora:RomipThing rdf:nodeID="bnodeD4015758-35E9-43C6-8E34-5BB70F0C7CB3">
		<Basic:identifier xml:lang="ru-RU">лидера нации</Basic:identifier>
		<rdfs:label xml:lang="ru-RU">лидера нации</rdfs:label>
	</RomipAnaphora:RomipThing>
	<RomipAnaphora:RomipThing rdf:nodeID="bnode40923F9E-7C96-427B-ACCD-85AAC4BEA812">
		<Basic:identifier xml:lang="ru-RU">этой республики</Basic:identifier>
		<rdfs:label xml:lang="ru-RU">этой республики</rdfs:label>
	</RomipAnaphora:RomipThing>
	<RomipAnaphora:RomipThing rdf:nodeID="bnodeD2DA48E1-E3F1-4CCE-8BF3-DF665CD878E8">
		<Basic:identifier xml:lang="ru-RU">глава этой республики Нурсултан Назарбаев</Basic:identifier>
		<rdfs:label xml:lang="ru-RU">глава этой республики Нурсултан Назарбаев</rdfs:label>
	</RomipAnaphora:RomipThing>
	<RomipAnaphora:RomipThing rdf:nodeID="bnode1170BD55-0986-4059-BD88-4398B649DB27">
		<Basic:identifier xml:lang="ru-RU">бессменный глава этой республики Нурсултан Назарбаев</Basic:identifier>
		<rdfs:label xml:lang="ru-RU">бессменный глава этой республики Нурсултан Назарбаев</rdfs:label>
	</RomipAnaphora:RomipThing>
	<RomipAnaphora:RomipThing rdf:nodeID="bnodeEDF73C35-928D-4AF0-8C77-A04C2C5D588F">
		<Basic:identifier xml:lang="ru-RU">поправку в конституцию, в соответствии с которой бессменный глава этой республики Нурсултан Назарбаев наделяется исключительным статусом — лидера нации</Basic:identifier>
		<rdfs:label xml:lang="ru-RU">поправку в конституцию, в соответствии с которой бессменный глава этой республики Нурсултан Назарбаев наделяется исключительным статусом — лидера нации</rdfs:label>
	</RomipAnaphora:RomipThing>
	<RomipAnaphora:RomipThing rdf:nodeID="bnodeCD629584-A832-421F-BEB8-6E1D2B6743B2">
		<Basic:identifier xml:lang="ru-RU">Казахстана</Basic:identifier>
		<rdfs:label xml:lang="ru-RU">Казахстана</rdfs:label>
	</RomipAnaphora:RomipThing>
	<RomipAnaphora:RomipThing rdf:nodeID="bnode7D1A5669-3094-439F-AD7E-2DD1D23D349A">
		<Basic:identifier xml:lang="ru-RU">законодатели Казахстана</Basic:identifier>
		<rdfs:label xml:lang="ru-RU">законодатели Казахстана</rdfs:label>
	</RomipAnaphora:RomipThing>
	<RomipAnaphora:RomipThing rdf:nodeID="bnode1E4B5908-E120-4C59-9A83-DFFC452EADFE">
		<Basic:identifier xml:lang="ru-RU">правительства</Basic:identifier>
		<rdfs:label xml:lang="ru-RU">правительство</rdfs:label>
	</RomipAnaphora:RomipThing>
	<RomipAnaphora:RomipThing rdf:nodeID="bnodeACD7DDDA-FC1D-4A4D-BE34-F2190FE8A4C2">
		<Basic:identifier xml:lang="ru-RU">главой правительства</Basic:identifier>
		<rdfs:label xml:lang="ru-RU">главой правительства</rdfs:label>
	</RomipAnaphora:RomipThing>
	<RomipAnaphora:RomipThing rdf:nodeID="bnode516E9B0B-C07C-4E48-AE9A-AB22DF369AF8">
		<Basic:identifier xml:lang="ru-RU">палат</Basic:identifier>
		<rdfs:label xml:lang="ru-RU">палаты</rdfs:label>
	</RomipAnaphora:RomipThing>
	<RomipAnaphora:RomipThing rdf:nodeID="bnodeB869AE47-1A6B-4A0F-8392-B0CF8E4C6D64">
		<Basic:identifier xml:lang="ru-RU">спикерами палат</Basic:identifier>
		<rdfs:label xml:lang="ru-RU">спикерами палат</rdfs:label>
	</RomipAnaphora:RomipThing>
	<RomipAnaphora:RomipThing rdf:nodeID="bnode059B012E-BF45-4A32-A3B8-AA059CDBC64B">
		<Basic:identifier xml:lang="ru-RU">президентом</Basic:identifier>
		<rdfs:label xml:lang="ru-RU">президентом</rdfs:label>
	</RomipAnaphora:RomipThing>
	<RomipAnaphora:RomipThing rdf:nodeID="bnode7A3268CF-1DB0-4247-B53F-8F331248F668">
		<Basic:identifier xml:lang="ru-RU">закон, который был одобрен не президентом, а спикерами палат и главой правительства</Basic:identifier>
		<rdfs:label xml:lang="ru-RU">закон, который будет одобрен не президентом, а спикерами палат и главой правительства</rdfs:label>
	</RomipAnaphora:RomipThing>
	<RomipAnaphora:RomipThing rdf:nodeID="bnodeCA58CFF1-B29D-4C21-9636-2F8DC424AFEE">
		<Basic:identifier xml:lang="ru-RU">Казахстане</Basic:identifier>
		<rdfs:label xml:lang="ru-RU">Казахстане</rdfs:label>
	</RomipAnaphora:RomipThing>
	<RomipAnaphora:RomipThing rdf:nodeID="bnodeF96148B0-0656-4993-BDC3-A2C5EF28EF60">
		<Basic:identifier xml:lang="ru-RU">нового закона</Basic:identifier>
		<rdfs:label xml:lang="ru-RU">нового закона</rdfs:label>
	</RomipAnaphora:RomipThing>
	<RomipAnaphora:RomipThing rdf:nodeID="bnodeD9190993-5994-412F-96B8-25FDD44A0260">
		<Basic:identifier xml:lang="ru-RU">текст нового закона, который уже, кстати, опубликован</Basic:identifier>
		<rdfs:label xml:lang="ru-RU">текст нового закона, который уже, кстати, опубликован</rdfs:label>
	</RomipAnaphora:RomipThing>
	<RomipAnaphora:RomipThing rdf:nodeID="bnode60C8F8AA-7D6B-4E37-9873-81B9DAFD101D">
		<Basic:identifier xml:lang="ru-RU">NEWSru.com</Basic:identifier>
		<rdfs:label xml:lang="ru-RU">NEWSru.com</rdfs:label>
	</RomipAnaphora:RomipThing>
	<RomipAnaphora:RomipThing rdf:nodeID="bnode5F769400-F12A-49CD-9194-2B25AE2947D6">
		<Basic:identifier xml:lang="ru-RU">его</Basic:identifier>
		<rdfs:label xml:lang="ru-RU">его</rdfs:label>
	</RomipAnaphora:RomipThing>
	<RomipAnaphora:RomipThing rdf:nodeID="bnode71D45365-6196-4F32-A6A9-3EA792F17AFF">
		<Basic:identifier xml:lang="ru-RU">этих должностных лиц</Basic:identifier>
		<rdfs:label xml:lang="ru-RU">эти должностные лица</rdfs:label>
	</RomipAnaphora:RomipThing>
	<RomipAnaphora:RomipThing rdf:nodeID="bnodeC101A21D-7371-48F0-9B4B-B47EC5618214">
		<Basic:identifier xml:lang="ru-RU">настоящего конституционного закона</Basic:identifier>
		<rdfs:label xml:lang="ru-RU">настоящего конституционного закона</rdfs:label>
	</RomipAnaphora:RomipThing>
	<RomipAnaphora:RomipThing rdf:nodeID="bnode6CA682C2-4CC9-4800-9A9E-B0C1E6244486">
		<Basic:identifier xml:lang="ru-RU">премьер-министра Масимова Карима</Basic:identifier>
		<rdfs:label xml:lang="ru-RU">премьер-министра Масимова Карима</rdfs:label>
	</RomipAnaphora:RomipThing>
	<RomipAnaphora:RomipThing rdf:nodeID="bnode7049EFD3-B0C3-49D1-970A-5ED9149760C4">
		<Basic:identifier xml:lang="ru-RU">парламента</Basic:identifier>
		<rdfs:label xml:lang="ru-RU">парламента</rdfs:label>
	</RomipAnaphora:RomipThing>
	<RomipAnaphora:RomipThing rdf:nodeID="bnode28F79210-AC03-4A77-90AF-24328E6B3F68">
		<Basic:identifier xml:lang="ru-RU">председателя мажилиса парламента Мухамеджанова Урала</Basic:identifier>
		<rdfs:label xml:lang="ru-RU">председатель Мажилиса парламента Мухамеджанова Урала</rdfs:label>
	</RomipAnaphora:RomipThing>
	<RomipAnaphora:RomipThing rdf:nodeID="bnode1F5C0F9E-DB72-4493-93C9-5979841C8E6F">
		<Basic:identifier xml:lang="ru-RU">парламента</Basic:identifier>
		<rdfs:label xml:lang="ru-RU">парламента</rdfs:label>
	</RomipAnaphora:RomipThing>
	<RomipAnaphora:RomipThing rdf:nodeID="bnode5033D171-E2C3-42E9-A9CA-F7EB786FC2F0">
		<Basic:identifier xml:lang="ru-RU">подписями председателя сената парламента Токаева Касым-Жомарта, председателя мажилиса парламента Мухамеджанова Урала, премьер-министра Масимова Карима</Basic:identifier>
		<rdfs:label xml:lang="ru-RU">подписями председателя сената парламента Токаева Касым-Жомарта, председателя мажилиса парламента Мухамеджанова Урала, премьер-министра Масимова Карима</rdfs:label>
	</RomipAnaphora:RomipThing>
	<RomipAnaphora:RomipThing rdf:nodeID="bnodeEA39F6E5-4A94-4A45-BF1A-0DF8EFAE4592">
		<Basic:identifier xml:lang="ru-RU">Настоящий конституционный закон</Basic:identifier>
		<rdfs:label xml:lang="ru-RU">Настоящий конституционный закон</rdfs:label>
	</RomipAnaphora:RomipThing>
	<RomipAnaphora:RomipThing rdf:nodeID="bnode33FD8168-AD88-474E-A022-79C22DD7E05A">
		<Basic:identifier xml:lang="ru-RU">своему вождю</Basic:identifier>
		<rdfs:label xml:lang="ru-RU">своему вождю</rdfs:label>
	</RomipAnaphora:RomipThing>
	<RomipAnaphora:RomipThing rdf:nodeID="bnodeC7DA0A53-605B-4AC7-9A2D-272D276110CA">
		<Basic:identifier xml:lang="ru-RU">законе о первом президенте</Basic:identifier>
		<rdfs:label xml:lang="ru-RU">законе о первом президенте</rdfs:label>
	</RomipAnaphora:RomipThing>
	<RomipAnaphora:RomipThing rdf:nodeID="bnodeC0D44AD2-A6C0-4786-A671-4896B7579673">
		<Basic:identifier xml:lang="ru-RU">конституции</Basic:identifier>
		<rdfs:label xml:lang="ru-RU">конституция</rdfs:label>
	</RomipAnaphora:RomipThing>
	<RomipAnaphora:RomipThing rdf:nodeID="bnodeC2AFCF56-CC81-4C50-A442-FE09DFC25513">
		<Basic:identifier xml:lang="ru-RU">его</Basic:identifier>
		<rdfs:label xml:lang="ru-RU">его</rdfs:label>
	</RomipAnaphora:RomipThing>
	<RomipAnaphora:RomipThing rdf:nodeID="bnode0C4F9855-A28E-437F-880A-38CF7AC262BC">
		<Basic:identifier xml:lang="ru-RU">данный документ</Basic:identifier>
		<rdfs:label xml:lang="ru-RU">данный документ</rdfs:label>
	</RomipAnaphora:RomipThing>
	<RomipAnaphora:RomipThing rdf:nodeID="bnodeE6DAB17C-60A9-4741-A806-6495836DB61D">
		<Basic:identifier xml:lang="ru-RU">этого статуса</Basic:identifier>
		<rdfs:label xml:lang="ru-RU">этого статуса</rdfs:label>
	</RomipAnaphora:RomipThing>
	<RomipAnaphora:RomipThing rdf:nodeID="bnode943CA4B1-F896-49FC-B745-43BF82B744B2">
		<Basic:identifier xml:lang="ru-RU">Нурсултан Назарбаев</Basic:identifier>
		<rdfs:label xml:lang="ru-RU">Нурсултан Назарбаев</rdfs:label>
	</RomipAnaphora:RomipThing>
	<RomipAnaphora:RomipThing rdf:nodeID="bnodeABDE57C8-36BA-455A-9DE0-B51ABAA541ED">
		<Basic:identifier xml:lang="ru-RU">республики</Basic:identifier>
		<rdfs:label xml:lang="ru-RU">республика</rdfs:label>
	</RomipAnaphora:RomipThing>
	<RomipAnaphora:RomipThing rdf:nodeID="bnodeB965393C-A6E2-434D-85E4-251C0952C100">
		<Basic:identifier xml:lang="ru-RU">премьера республики</Basic:identifier>
		<rdfs:label xml:lang="ru-RU">премьера республики</rdfs:label>
	</RomipAnaphora:RomipThing>
	<RomipAnaphora:RomipThing rdf:nodeID="bnode379C36EB-83C6-42C5-8967-8B779F6E91B8">
		<Basic:identifier xml:lang="ru-RU">парламента</Basic:identifier>
		<rdfs:label xml:lang="ru-RU">парламента</rdfs:label>
	</RomipAnaphora:RomipThing>
	<RomipAnaphora:RomipThing rdf:nodeID="bnode1203AD64-7230-4CCB-BBC9-8D2DBE30ED9B">
		<Basic:identifier xml:lang="ru-RU">палат парламента</Basic:identifier>
		<rdfs:label xml:lang="ru-RU">палаты парламента</rdfs:label>
	</RomipAnaphora:RomipThing>
	<RomipAnaphora:RomipThing rdf:nodeID="bnode5952DFC9-4CFC-4C2B-BFB7-426BBF9C81DE">
		<Basic:identifier xml:lang="ru-RU">глав обеих палат парламента</Basic:identifier>
		<rdfs:label xml:lang="ru-RU">главы обеих палат парламента</rdfs:label>
	</RomipAnaphora:RomipThing>
	<RomipAnaphora:RomipThing rdf:nodeID="bnodeAB492EBD-6B7E-4EDB-8091-DB70035D4D5A">
		<Basic:identifier xml:lang="ru-RU">подписи глав обеих палат парламента, а также премьера республики</Basic:identifier>
		<rdfs:label xml:lang="ru-RU">подписи глав обеих палат парламента, а также премьера республики</rdfs:label>
	</RomipAnaphora:RomipThing>
	<RomipAnaphora:RomipThing rdf:nodeID="bnodeC1BADC67-4441-4065-BD92-84BE17DD003D">
		<Basic:identifier xml:lang="ru-RU">закон «О лидере нации»</Basic:identifier>
		<rdfs:label xml:lang="ru-RU">закон «О лидере нации»</rdfs:label>
	</RomipAnaphora:RomipThing>
	<RomipAnaphora:RomipThing rdf:nodeID="bnodeFACB2842-66A2-4379-BB75-52481E9F615B">
		<Basic:identifier xml:lang="ru-RU">Казахстане</Basic:identifier>
		<rdfs:label xml:lang="ru-RU">Казахстане</rdfs:label>
	</RomipAnaphora:RomipThing>
	<RomipAnaphora:RomipThing rdf:nodeID="bnodeCCF565BD-38B9-4229-B8FD-44F2BF1B85BD">
		<Basic:identifier xml:lang="ru-RU">нации</Basic:identifier>
		<rdfs:label xml:lang="ru-RU">нация</rdfs:label>
	</RomipAnaphora:RomipThing>
	<RomipAnaphora:RomipThing rdf:nodeID="bnode6A051EF9-35D3-4CAF-AED8-A756199C47F7">
		<Basic:identifier xml:lang="ru-RU">лидером нации</Basic:identifier>
		<rdfs:label xml:lang="ru-RU">лидером нации</rdfs:label>
	</RomipAnaphora:RomipThing>
	<RomipAnaphora:RomipThing rdf:nodeID="bnode7F357075-8FC5-4111-AE3C-56D3889809FD">
		<Basic:identifier xml:lang="ru-RU">Нурсултан Назарбаев</Basic:identifier>
		<rdfs:label xml:lang="ru-RU">Нурсултан Назарбаев</rdfs:label>
	</RomipAnaphora:RomipThing>
	<RomipAnaphora:RomipThing rdf:nodeID="bnodeEFE37480-880C-4F8E-AB97-1D15974EA4B1"/>
	<RomipAnaphora:RomipThing rdf:nodeID="bnode0779D0D3-8281-4679-9AA4-10F5BF1CD263"/>
	<RomipAnaphora:RomipThing rdf:nodeID="bnode0CF6B95C-C279-468A-B0B7-14A38B6DF2C0"/>
	<RomipAnaphora:RomipThing rdf:nodeID="bnode9E6B2BE4-55E6-4A41-8CAE-6B6E5320967B"/>
	<RomipAnaphora:RomipThing rdf:nodeID="bnode2CE9EB55-27BC-4CA8-B90E-F1C398208A8A"/>
	<RomipAnaphora:RomipThing rdf:nodeID="bnodeC1DEEA94-A028-48A0-B3AA-83849984AB99"/>
	<RomipAnaphora:RomipThing rdf:nodeID="bnode5C89A026-B330-4DC7-9C03-53E27A1EC8A5"/>
	<Aux:TextAnnotations rdf:nodeID="bnodeABFBC6EF-4C74-4777-BD38-275DA877C6FF">
		<Aux:document_text xml:lang="ru-RU">Не хочется, а надо Нурсултан Назарбаев против воли стал лидером нации.  15 июня в Казахстане начал действовать закон «О лидере нации», под которым стоят подписи глав обеих палат парламента, а также премьера республики. Напомним, что сам Нурсултан Назарбаев ранее отказался от этого статуса и не стал подписывать данный документ, мотивируя отказ тем, что новые гарантии защиты его чести, достоинства и неприкосновенности уже и так прописаны в конституции, а также законе о первом президенте и прочих нормативных актах. Тем не менее парламентарии и министры рассудили этот вопрос по-своему и на свой лад продемонстрировали верность и любовь к своему вождю. «Настоящий конституционный закон скреплён подписями председателя сената парламента Токаева Касым-Жомарта, председателя мажилиса парламента Мухамеджанова Урала, премьер-министра Масимова Карима, что свидетельствует о юридической корректности настоящего конституционного закона и о юридической ответственности этих должностных лиц за его законность», — цитирует NEWSru.com текст нового закона, который уже, кстати, опубликован. Таким образом, в Казахстане впервые начинает действовать закон, который был одобрен не президентом, а спикерами палат и главой правительства.  Напомним, 13 мая законодатели Казахстана единогласно одобрили поправку в конституцию, в соответствии с которой бессменный глава этой республики Нурсултан Назарбаев наделяется исключительным статусом — лидера нации. Законодательные изменения предусматривают уголовную ответственность за публичное оскорбление и иное посягательство на честь и достоинство лидера нации, осквернение его изображений, воспрепятствование его законной деятельности. Посягательство на жизнь Назарбаева отныне приравнивается к терроризму. Тот же документ запрещает подвергать лидера нации задержанию, аресту и личному досмотру, привлечению к уголовной или административной ответственности за деяния, совершённые им в период исполнения полномочий президента, а после их прекращения — связанные с осуществлением своего статуса первого президента Казахстана — лидера нации. Отметим, что до сих пор глава Казахстана старался избегать слишком сильных «проявлений любви» от своих подчинённых. В частности, он запретил переименовывать столицу республики из Астаны в Нурсултан, а главам областных администраций не позволил устраивать пышные празднества по поводу своего 70-летнего юбилея. Останется ли Назарбаев таким же скромным в статусе лидера нации, покажет время. </Aux:document_text>
		<Aux:annotation>
			<Aux:InstanceAnnotation rdf:nodeID="bnode1F2DDFC6-85AA-469F-A72E-D8839F570C6C">
				<Aux:annotation_start rdf:datatype="http://www.w3.org/2001/XMLSchema#integer">19</Aux:annotation_start>
				<Aux:annotation_end rdf:datatype="http://www.w3.org/2001/XMLSchema#integer">38</Aux:annotation_end>
				<Aux:instance rdf:nodeID="bnode7F357075-8FC5-4111-AE3C-56D3889809FD"/>
			</Aux:InstanceAnnotation>
		</Aux:annotation>
		<Aux:annotation>
			<Aux:InstanceAnnotation rdf:nodeID="bnode8D8AE15F-340B-4A0E-AAFD-747207576C00">
				<Aux:annotation_start rdf:datatype="http://www.w3.org/2001/XMLSchema#integer">56</Aux:annotation_start>
				<Aux:annotation_end rdf:datatype="http://www.w3.org/2001/XMLSchema#integer">69</Aux:annotation_end>
				<Aux:instance rdf:nodeID="bnode6A051EF9-35D3-4CAF-AED8-A756199C47F7"/>
			</Aux:InstanceAnnotation>
		</Aux:annotation>
		<Aux:annotation>
			<Aux:InstanceAnnotation rdf:nodeID="bnode0DF3B9C1-1E7C-485F-A3CB-224FEE4AD2CF">
				<Aux:annotation_start rdf:datatype="http://www.w3.org/2001/XMLSchema#integer">64</Aux:annotation_start>
				<Aux:annotation_end rdf:datatype="http://www.w3.org/2001/XMLSchema#integer">69</Aux:annotation_end>
				<Aux:instance rdf:nodeID="bnodeCCF565BD-38B9-4229-B8FD-44F2BF1B85BD"/>
			</Aux:InstanceAnnotation>
		</Aux:annotation>
		<Aux:annotation>
			<Aux:InstanceAnnotation rdf:nodeID="bnode605C03E1-2E19-439E-A667-F757335A7DF9">
				<Aux:annotation_start rdf:datatype="http://www.w3.org/2001/XMLSchema#integer">82</Aux:annotation_start>
				<Aux:annotation_end rdf:datatype="http://www.w3.org/2001/XMLSchema#integer">92</Aux:annotation_end>
				<Aux:instance rdf:nodeID="bnodeFACB2842-66A2-4379-BB75-52481E9F615B"/>
			</Aux:InstanceAnnotation>
		</Aux:annotation>
		<Aux:annotation>
			<Aux:InstanceAnnotation rdf:nodeID="bnode6BB71059-DF89-4035-A9F5-4AC70B6D5ADA">
				<Aux:annotation_start rdf:datatype="http://www.w3.org/2001/XMLSchema#integer">111</Aux:annotation_start>
				<Aux:annotation_end rdf:datatype="http://www.w3.org/2001/XMLSchema#integer">133</Aux:annotation_end>
				<Aux:instance rdf:nodeID="bnodeC1BADC67-4441-4065-BD92-84BE17DD003D"/>
			</Aux:InstanceAnnotation>
		</Aux:annotation>
		<Aux:annotation>
			<Aux:InstanceAnnotation rdf:nodeID="bnodeBF727F34-5DF7-4E23-8AB8-A16636AB0600">
				<Aux:annotation_start rdf:datatype="http://www.w3.org/2001/XMLSchema#integer">153</Aux:annotation_start>
				<Aux:annotation_end rdf:datatype="http://www.w3.org/2001/XMLSchema#integer">217</Aux:annotation_end>
				<Aux:instance rdf:nodeID="bnodeAB492EBD-6B7E-4EDB-8091-DB70035D4D5A"/>
			</Aux:InstanceAnnotation>
		</Aux:annotation>
		<Aux:annotation>
			<Aux:InstanceAnnotation rdf:nodeID="bnode9983874A-19BD-46F1-80FD-D170B1A4FA9B">
				<Aux:annotation_start rdf:datatype="http://www.w3.org/2001/XMLSchema#integer">161</Aux:annotation_start>
				<Aux:annotation_end rdf:datatype="http://www.w3.org/2001/XMLSchema#integer">188</Aux:annotation_end>
				<Aux:instance rdf:nodeID="bnode5952DFC9-4CFC-4C2B-BFB7-426BBF9C81DE"/>
			</Aux:InstanceAnnotation>
		</Aux:annotation>
		<Aux:annotation>
			<Aux:InstanceAnnotation rdf:nodeID="bnodeA228F702-053A-400B-8E9B-1671BD8358CD">
				<Aux:annotation_start rdf:datatype="http://www.w3.org/2001/XMLSchema#integer">172</Aux:annotation_start>
				<Aux:annotation_end rdf:datatype="http://www.w3.org/2001/XMLSchema#integer">188</Aux:annotation_end>
				<Aux:instance rdf:nodeID="bnode1203AD64-7230-4CCB-BBC9-8D2DBE30ED9B"/>
			</Aux:InstanceAnnotation>
		</Aux:annotation>
		<Aux:annotation>
			<Aux:InstanceAnnotation rdf:nodeID="bnodeB7606271-9075-41ED-ABCC-0AA2FD9CD8D8">
				<Aux:annotation_start rdf:datatype="http://www.w3.org/2001/XMLSchema#integer">178</Aux:annotation_start>
				<Aux:annotation_end rdf:datatype="http://www.w3.org/2001/XMLSchema#integer">188</Aux:annotation_end>
				<Aux:instance rdf:nodeID="bnode379C36EB-83C6-42C5-8967-8B779F6E91B8"/>
			</Aux:InstanceAnnotation>
		</Aux:annotation>
		<Aux:annotation>
			<Aux:InstanceAnnotation rdf:nodeID="bnode81DF6B51-03B4-40B4-BF2F-6AED082C2C47">
				<Aux:annotation_start rdf:datatype="http://www.w3.org/2001/XMLSchema#integer">198</Aux:annotation_start>
				<Aux:annotation_end rdf:datatype="http://www.w3.org/2001/XMLSchema#integer">217</Aux:annotation_end>
				<Aux:instance rdf:nodeID="bnodeB965393C-A6E2-434D-85E4-251C0952C100"/>
			</Aux:InstanceAnnotation>
		</Aux:annotation>
		<Aux:annotation>
			<Aux:InstanceAnnotation rdf:nodeID="bnode80EE3521-434D-45AE-8690-E03DBC40327A">
				<Aux:annotation_start rdf:datatype="http://www.w3.org/2001/XMLSchema#integer">207</Aux:annotation_start>
				<Aux:annotation_end rdf:datatype="http://www.w3.org/2001/XMLSchema#integer">217</Aux:annotation_end>
				<Aux:instance rdf:nodeID="bnodeABDE57C8-36BA-455A-9DE0-B51ABAA541ED"/>
			</Aux:InstanceAnnotation>
		</Aux:annotation>
		<Aux:annotation>
			<Aux:InstanceAnnotation rdf:nodeID="bnodeB2790B2A-33ED-4FF8-9F9F-06015416FAE7">
				<Aux:annotation_start rdf:datatype="http://www.w3.org/2001/XMLSchema#integer">237</Aux:annotation_start>
				<Aux:annotation_end rdf:datatype="http://www.w3.org/2001/XMLSchema#integer">256</Aux:annotation_end>
				<Aux:instance rdf:nodeID="bnode943CA4B1-F896-49FC-B745-43BF82B744B2"/>
			</Aux:InstanceAnnotation>
		</Aux:annotation>
		<Aux:annotation>
			<Aux:InstanceAnnotation rdf:nodeID="bnode049F3438-5A20-42B1-BD07-DBED06CBEEB2">
				<Aux:annotation_start rdf:datatype="http://www.w3.org/2001/XMLSchema#integer">276</Aux:annotation_start>
				<Aux:annotation_end rdf:datatype="http://www.w3.org/2001/XMLSchema#integer">289</Aux:annotation_end>
				<Aux:instance rdf:nodeID="bnodeE6DAB17C-60A9-4741-A806-6495836DB61D"/>
			</Aux:InstanceAnnotation>
		</Aux:annotation>
		<Aux:annotation>
			<Aux:InstanceAnnotation rdf:nodeID="bnode7BB73203-8331-40BA-80BB-57CA20F70E45">
				<Aux:annotation_start rdf:datatype="http://www.w3.org/2001/XMLSchema#integer">312</Aux:annotation_start>
				<Aux:annotation_end rdf:datatype="http://www.w3.org/2001/XMLSchema#integer">327</Aux:annotation_end>
				<Aux:instance rdf:nodeID="bnode0C4F9855-A28E-437F-880A-38CF7AC262BC"/>
			</Aux:InstanceAnnotation>
		</Aux:annotation>
		<Aux:annotation>
			<Aux:InstanceAnnotation rdf:nodeID="bnodeB3A337E5-BE92-4D68-9BFE-F0DE7CDA2D7B">
				<Aux:annotation_start rdf:datatype="http://www.w3.org/2001/XMLSchema#integer">376</Aux:annotation_start>
				<Aux:annotation_end rdf:datatype="http://www.w3.org/2001/XMLSchema#integer">379</Aux:annotation_end>
				<Aux:instance rdf:nodeID="bnodeC2AFCF56-CC81-4C50-A442-FE09DFC25513"/>
			</Aux:InstanceAnnotation>
		</Aux:annotation>
		<Aux:annotation>
			<Aux:InstanceAnnotation rdf:nodeID="bnode2FBC4E77-F53C-4B3F-A3D6-754CA1954A50">
				<Aux:annotation_start rdf:datatype="http://www.w3.org/2001/XMLSchema#integer">442</Aux:annotation_start>
				<Aux:annotation_end rdf:datatype="http://www.w3.org/2001/XMLSchema#integer">453</Aux:annotation_end>
				<Aux:instance rdf:nodeID="bnodeC0D44AD2-A6C0-4786-A671-4896B7579673"/>
			</Aux:InstanceAnnotation>
		</Aux:annotation>
		<Aux:annotation>
			<Aux:InstanceAnnotation rdf:nodeID="bnode33385BF9-DBF1-4706-BBF3-A91F00E440F7">
				<Aux:annotation_start rdf:datatype="http://www.w3.org/2001/XMLSchema#integer">463</Aux:annotation_start>
				<Aux:annotation_end rdf:datatype="http://www.w3.org/2001/XMLSchema#integer">489</Aux:annotation_end>
				<Aux:instance rdf:nodeID="bnodeC7DA0A53-605B-4AC7-9A2D-272D276110CA"/>
			</Aux:InstanceAnnotation>
		</Aux:annotation>
		<Aux:annotation>
			<Aux:InstanceAnnotation rdf:nodeID="bnodeA0FC0297-6430-4238-83CD-B1B52207E00D">
				<Aux:annotation_start rdf:datatype="http://www.w3.org/2001/XMLSchema#integer">641</Aux:annotation_start>
				<Aux:annotation_end rdf:datatype="http://www.w3.org/2001/XMLSchema#integer">653</Aux:annotation_end>
				<Aux:instance rdf:nodeID="bnode33FD8168-AD88-474E-A022-79C22DD7E05A"/>
			</Aux:InstanceAnnotation>
		</Aux:annotation>
		<Aux:annotation>
			<Aux:InstanceAnnotation rdf:nodeID="bnodeA67286EB-08D3-47AD-B123-1E330F31D42A">
				<Aux:annotation_start rdf:datatype="http://www.w3.org/2001/XMLSchema#integer">656</Aux:annotation_start>
				<Aux:annotation_end rdf:datatype="http://www.w3.org/2001/XMLSchema#integer">687</Aux:annotation_end>
				<Aux:instance rdf:nodeID="bnodeEA39F6E5-4A94-4A45-BF1A-0DF8EFAE4592"/>
			</Aux:InstanceAnnotation>
		</Aux:annotation>
		<Aux:annotation>
			<Aux:InstanceAnnotation rdf:nodeID="bnodeD4243E62-E6C8-489E-B55C-707CC1A60586">
				<Aux:annotation_start rdf:datatype="http://www.w3.org/2001/XMLSchema#integer">697</Aux:annotation_start>
				<Aux:annotation_end rdf:datatype="http://www.w3.org/2001/XMLSchema#integer">847</Aux:annotation_end>
				<Aux:instance rdf:nodeID="bnode5033D171-E2C3-42E9-A9CA-F7EB786FC2F0"/>
			</Aux:InstanceAnnotation>
		</Aux:annotation>
		<Aux:annotation>
			<Aux:InstanceAnnotation rdf:nodeID="bnode9353E67A-1FBC-4845-99FF-C1F7F809494F">
				<Aux:annotation_start rdf:datatype="http://www.w3.org/2001/XMLSchema#integer">727</Aux:annotation_start>
				<Aux:annotation_end rdf:datatype="http://www.w3.org/2001/XMLSchema#integer">737</Aux:annotation_end>
				<Aux:instance rdf:nodeID="bnode1F5C0F9E-DB72-4493-93C9-5979841C8E6F"/>
			</Aux:InstanceAnnotation>
		</Aux:annotation>
		<Aux:annotation>
			<Aux:InstanceAnnotation rdf:nodeID="bnode9A4CAB39-FC2E-477A-87A6-F28C1C2E638A">
				<Aux:annotation_start rdf:datatype="http://www.w3.org/2001/XMLSchema#integer">761</Aux:annotation_start>
				<Aux:annotation_end rdf:datatype="http://www.w3.org/2001/XMLSchema#integer">813</Aux:annotation_end>
				<Aux:instance rdf:nodeID="bnode28F79210-AC03-4A77-90AF-24328E6B3F68"/>
			</Aux:InstanceAnnotation>
		</Aux:annotation>
		<Aux:annotation>
			<Aux:InstanceAnnotation rdf:nodeID="bnode3ACCFA82-565D-4B94-8EDE-0688C63B1761">
				<Aux:annotation_start rdf:datatype="http://www.w3.org/2001/XMLSchema#integer">783</Aux:annotation_start>
				<Aux:annotation_end rdf:datatype="http://www.w3.org/2001/XMLSchema#integer">793</Aux:annotation_end>
				<Aux:instance rdf:nodeID="bnode7049EFD3-B0C3-49D1-970A-5ED9149760C4"/>
			</Aux:InstanceAnnotation>
		</Aux:annotation>
		<Aux:annotation>
			<Aux:InstanceAnnotation rdf:nodeID="bnode1CBB99AC-61AC-41DB-A02E-C099AD2A39E7">
				<Aux:annotation_start rdf:datatype="http://www.w3.org/2001/XMLSchema#integer">815</Aux:annotation_start>
				<Aux:annotation_end rdf:datatype="http://www.w3.org/2001/XMLSchema#integer">847</Aux:annotation_end>
				<Aux:instance rdf:nodeID="bnode6CA682C2-4CC9-4800-9A9E-B0C1E6244486"/>
			</Aux:InstanceAnnotation>
		</Aux:annotation>
		<Aux:annotation>
			<Aux:InstanceAnnotation rdf:nodeID="bnode4B47DCF9-C1E9-46FF-BCBC-5CB830D02F00">
				<Aux:annotation_start rdf:datatype="http://www.w3.org/2001/XMLSchema#integer">896</Aux:annotation_start>
				<Aux:annotation_end rdf:datatype="http://www.w3.org/2001/XMLSchema#integer">930</Aux:annotation_end>
				<Aux:instance rdf:nodeID="bnodeC101A21D-7371-48F0-9B4B-B47EC5618214"/>
			</Aux:InstanceAnnotation>
		</Aux:annotation>
		<Aux:annotation>
			<Aux:InstanceAnnotation rdf:nodeID="bnode15ED37D9-B171-4111-8AF6-DFBABCC6DF96">
				<Aux:annotation_start rdf:datatype="http://www.w3.org/2001/XMLSchema#integer">963</Aux:annotation_start>
				<Aux:annotation_end rdf:datatype="http://www.w3.org/2001/XMLSchema#integer">983</Aux:annotation_end>
				<Aux:instance rdf:nodeID="bnode71D45365-6196-4F32-A6A9-3EA792F17AFF"/>
			</Aux:InstanceAnnotation>
		</Aux:annotation>
		<Aux:annotation>
			<Aux:InstanceAnnotation rdf:nodeID="bnodeF7C67640-BBE5-42EA-A6B6-D0C26ABBFFDA">
				<Aux:annotation_start rdf:datatype="http://www.w3.org/2001/XMLSchema#integer">987</Aux:annotation_start>
				<Aux:annotation_end rdf:datatype="http://www.w3.org/2001/XMLSchema#integer">990</Aux:annotation_end>
				<Aux:instance rdf:nodeID="bnode5F769400-F12A-49CD-9194-2B25AE2947D6"/>
			</Aux:InstanceAnnotation>
		</Aux:annotation>
		<Aux:annotation>
			<Aux:InstanceAnnotation rdf:nodeID="bnode6D808532-9769-4A1B-8391-99FEC48346D1">
				<Aux:annotation_start rdf:datatype="http://www.w3.org/2001/XMLSchema#integer">1015</Aux:annotation_start>
				<Aux:annotation_end rdf:datatype="http://www.w3.org/2001/XMLSchema#integer">1025</Aux:annotation_end>
				<Aux:instance rdf:nodeID="bnode60C8F8AA-7D6B-4E37-9873-81B9DAFD101D"/>
			</Aux:InstanceAnnotation>
		</Aux:annotation>
		<Aux:annotation>
			<Aux:InstanceAnnotation rdf:nodeID="bnode3318D447-9CCD-42F2-995A-D9AB54F9F143">
				<Aux:annotation_start rdf:datatype="http://www.w3.org/2001/XMLSchema#integer">1026</Aux:annotation_start>
				<Aux:annotation_end rdf:datatype="http://www.w3.org/2001/XMLSchema#integer">1079</Aux:annotation_end>
				<Aux:instance rdf:nodeID="bnodeD9190993-5994-412F-96B8-25FDD44A0260"/>
			</Aux:InstanceAnnotation>
		</Aux:annotation>
		<Aux:annotation>
			<Aux:InstanceAnnotation rdf:nodeID="bnode4AD3A86A-C0CE-48B6-BE4C-9BD164B63A39">
				<Aux:annotation_start rdf:datatype="http://www.w3.org/2001/XMLSchema#integer">1032</Aux:annotation_start>
				<Aux:annotation_end rdf:datatype="http://www.w3.org/2001/XMLSchema#integer">1045</Aux:annotation_end>
				<Aux:instance rdf:nodeID="bnodeF96148B0-0656-4993-BDC3-A2C5EF28EF60"/>
			</Aux:InstanceAnnotation>
		</Aux:annotation>
		<Aux:annotation>
			<Aux:InstanceAnnotation rdf:nodeID="bnode8541D443-36DD-4D3D-9001-189B83D6B17D">
				<Aux:annotation_start rdf:datatype="http://www.w3.org/2001/XMLSchema#integer">1098</Aux:annotation_start>
				<Aux:annotation_end rdf:datatype="http://www.w3.org/2001/XMLSchema#integer">1108</Aux:annotation_end>
				<Aux:instance rdf:nodeID="bnodeCA58CFF1-B29D-4C21-9636-2F8DC424AFEE"/>
			</Aux:InstanceAnnotation>
		</Aux:annotation>
		<Aux:annotation>
			<Aux:InstanceAnnotation rdf:nodeID="bnodeE4C74AE8-5E8B-4C4C-AC92-714E9507BE1A">
				<Aux:annotation_start rdf:datatype="http://www.w3.org/2001/XMLSchema#integer">1138</Aux:annotation_start>
				<Aux:annotation_end rdf:datatype="http://www.w3.org/2001/XMLSchema#integer">1221</Aux:annotation_end>
				<Aux:instance rdf:nodeID="bnode7A3268CF-1DB0-4247-B53F-8F331248F668"/>
			</Aux:InstanceAnnotation>
		</Aux:annotation>
		<Aux:annotation>
			<Aux:InstanceAnnotation rdf:nodeID="bnodeC46562BA-39F8-43A6-848D-CAE9654CBCFC">
				<Aux:annotation_start rdf:datatype="http://www.w3.org/2001/XMLSchema#integer">1168</Aux:annotation_start>
				<Aux:annotation_end rdf:datatype="http://www.w3.org/2001/XMLSchema#integer">1179</Aux:annotation_end>
				<Aux:instance rdf:nodeID="bnode059B012E-BF45-4A32-A3B8-AA059CDBC64B"/>
			</Aux:InstanceAnnotation>
		</Aux:annotation>
		<Aux:annotation>
			<Aux:InstanceAnnotation rdf:nodeID="bnode5956FDF9-9412-4623-943F-6E486C17A089">
				<Aux:annotation_start rdf:datatype="http://www.w3.org/2001/XMLSchema#integer">1183</Aux:annotation_start>
				<Aux:annotation_end rdf:datatype="http://www.w3.org/2001/XMLSchema#integer">1198</Aux:annotation_end>
				<Aux:instance rdf:nodeID="bnodeB869AE47-1A6B-4A0F-8392-B0CF8E4C6D64"/>
			</Aux:InstanceAnnotation>
		</Aux:annotation>
		<Aux:annotation>
			<Aux:InstanceAnnotation rdf:nodeID="bnode75BBD585-F019-40EB-B04D-C6F1F224FE30">
				<Aux:annotation_start rdf:datatype="http://www.w3.org/2001/XMLSchema#integer">1193</Aux:annotation_start>
				<Aux:annotation_end rdf:datatype="http://www.w3.org/2001/XMLSchema#integer">1198</Aux:annotation_end>
				<Aux:instance rdf:nodeID="bnode516E9B0B-C07C-4E48-AE9A-AB22DF369AF8"/>
			</Aux:InstanceAnnotation>
		</Aux:annotation>
		<Aux:annotation>
			<Aux:InstanceAnnotation rdf:nodeID="bnode5546DA05-FD96-4643-8B06-B2F4845BA099">
				<Aux:annotation_start rdf:datatype="http://www.w3.org/2001/XMLSchema#integer">1201</Aux:annotation_start>
				<Aux:annotation_end rdf:datatype="http://www.w3.org/2001/XMLSchema#integer">1221</Aux:annotation_end>
				<Aux:instance rdf:nodeID="bnodeACD7DDDA-FC1D-4A4D-BE34-F2190FE8A4C2"/>
			</Aux:InstanceAnnotation>
		</Aux:annotation>
		<Aux:annotation>
			<Aux:InstanceAnnotation rdf:nodeID="bnode8979B261-A657-40CA-980C-41CEEA1DA763">
				<Aux:annotation_start rdf:datatype="http://www.w3.org/2001/XMLSchema#integer">1208</Aux:annotation_start>
				<Aux:annotation_end rdf:datatype="http://www.w3.org/2001/XMLSchema#integer">1221</Aux:annotation_end>
				<Aux:instance rdf:nodeID="bnode1E4B5908-E120-4C59-9A83-DFFC452EADFE"/>
			</Aux:InstanceAnnotation>
		</Aux:annotation>
		<Aux:annotation>
			<Aux:InstanceAnnotation rdf:nodeID="bnode9AF08ADD-12DE-42DE-9F89-42DE749BB9CC">
				<Aux:annotation_start rdf:datatype="http://www.w3.org/2001/XMLSchema#integer">1241</Aux:annotation_start>
				<Aux:annotation_end rdf:datatype="http://www.w3.org/2001/XMLSchema#integer">1264</Aux:annotation_end>
				<Aux:instance rdf:nodeID="bnode7D1A5669-3094-439F-AD7E-2DD1D23D349A"/>
			</Aux:InstanceAnnotation>
		</Aux:annotation>
		<Aux:annotation>
			<Aux:InstanceAnnotation rdf:nodeID="bnode48F16ED3-F75E-42F1-BB3B-C94B9E81EF25">
				<Aux:annotation_start rdf:datatype="http://www.w3.org/2001/XMLSchema#integer">1254</Aux:annotation_start>
				<Aux:annotation_end rdf:datatype="http://www.w3.org/2001/XMLSchema#integer">1264</Aux:annotation_end>
				<Aux:instance rdf:nodeID="bnodeCD629584-A832-421F-BEB8-6E1D2B6743B2"/>
			</Aux:InstanceAnnotation>
		</Aux:annotation>
		<Aux:annotation>
			<Aux:InstanceAnnotation rdf:nodeID="bnode6E9B19C1-9155-4B43-B144-11B49A33C5EA">
				<Aux:annotation_start rdf:datatype="http://www.w3.org/2001/XMLSchema#integer">1286</Aux:annotation_start>
				<Aux:annotation_end rdf:datatype="http://www.w3.org/2001/XMLSchema#integer">1437</Aux:annotation_end>
				<Aux:instance rdf:nodeID="bnodeEDF73C35-928D-4AF0-8C77-A04C2C5D588F"/>
			</Aux:InstanceAnnotation>
		</Aux:annotation>
		<Aux:annotation>
			<Aux:InstanceAnnotation rdf:nodeID="bnode073563A0-06DF-46D3-8EF6-99FB7360418B">
				<Aux:annotation_start rdf:datatype="http://www.w3.org/2001/XMLSchema#integer">1335</Aux:annotation_start>
				<Aux:annotation_end rdf:datatype="http://www.w3.org/2001/XMLSchema#integer">1387</Aux:annotation_end>
				<Aux:instance rdf:nodeID="bnode1170BD55-0986-4059-BD88-4398B649DB27"/>
			</Aux:InstanceAnnotation>
		</Aux:annotation>
		<Aux:annotation>
			<Aux:InstanceAnnotation rdf:nodeID="bnode170A64A7-6F3F-4F36-8514-12418BC85C8A">
				<Aux:annotation_start rdf:datatype="http://www.w3.org/2001/XMLSchema#integer">1346</Aux:annotation_start>
				<Aux:annotation_end rdf:datatype="http://www.w3.org/2001/XMLSchema#integer">1387</Aux:annotation_end>
				<Aux:instance rdf:nodeID="bnodeD2DA48E1-E3F1-4CCE-8BF3-DF665CD878E8"/>
			</Aux:InstanceAnnotation>
		</Aux:annotation>
		<Aux:annotation>
			<Aux:InstanceAnnotation rdf:nodeID="bnodeEA6E1B54-4430-4792-9AAE-1C749C71797D">
				<Aux:annotation_start rdf:datatype="http://www.w3.org/2001/XMLSchema#integer">1352</Aux:annotation_start>
				<Aux:annotation_end rdf:datatype="http://www.w3.org/2001/XMLSchema#integer">1367</Aux:annotation_end>
				<Aux:instance rdf:nodeID="bnode40923F9E-7C96-427B-ACCD-85AAC4BEA812"/>
			</Aux:InstanceAnnotation>
		</Aux:annotation>
		<Aux:annotation>
			<Aux:InstanceAnnotation rdf:nodeID="bnode9C341E8C-89DE-4313-86AD-3B4FBABF80CF">
				<Aux:annotation_start rdf:datatype="http://www.w3.org/2001/XMLSchema#integer">1425</Aux:annotation_start>
				<Aux:annotation_end rdf:datatype="http://www.w3.org/2001/XMLSchema#integer">1437</Aux:annotation_end>
				<Aux:instance rdf:nodeID="bnodeD4015758-35E9-43C6-8E34-5BB70F0C7CB3"/>
			</Aux:InstanceAnnotation>
		</Aux:annotation>
		<Aux:annotation>
			<Aux:InstanceAnnotation rdf:nodeID="bnode710C3033-3566-4AFE-9336-296C64D32431">
				<Aux:annotation_start rdf:datatype="http://www.w3.org/2001/XMLSchema#integer">1432</Aux:annotation_start>
				<Aux:annotation_end rdf:datatype="http://www.w3.org/2001/XMLSchema#integer">1437</Aux:annotation_end>
				<Aux:instance rdf:nodeID="bnode6C1A3B95-9051-44D7-ABD1-544B6420898E"/>
			</Aux:InstanceAnnotation>
		</Aux:annotation>
		<Aux:annotation>
			<Aux:InstanceAnnotation rdf:nodeID="bnode2DACD063-3761-45D0-AC46-B611FAB449F4">
				<Aux:annotation_start rdf:datatype="http://www.w3.org/2001/XMLSchema#integer">1577</Aux:annotation_start>
				<Aux:annotation_end rdf:datatype="http://www.w3.org/2001/XMLSchema#integer">1589</Aux:annotation_end>
				<Aux:instance rdf:nodeID="bnodeA4ADA898-B244-45B5-89EC-9028ADFD339C"/>
			</Aux:InstanceAnnotation>
		</Aux:annotation>
		<Aux:annotation>
			<Aux:InstanceAnnotation rdf:nodeID="bnodeBA580F59-7A6E-4FBC-B706-6061CD7319CF">
				<Aux:annotation_start rdf:datatype="http://www.w3.org/2001/XMLSchema#integer">1584</Aux:annotation_start>
				<Aux:annotation_end rdf:datatype="http://www.w3.org/2001/XMLSchema#integer">1589</Aux:annotation_end>
				<Aux:instance rdf:nodeID="bnode4E9539B9-42A5-4085-9236-E1149E729E7F"/>
			</Aux:InstanceAnnotation>
		</Aux:annotation>
		<Aux:annotation>
			<Aux:InstanceAnnotation rdf:nodeID="bnodeC13CB621-A21C-455D-964D-BB309E971C83">
				<Aux:annotation_start rdf:datatype="http://www.w3.org/2001/XMLSchema#integer">1603</Aux:annotation_start>
				<Aux:annotation_end rdf:datatype="http://www.w3.org/2001/XMLSchema#integer">1606</Aux:annotation_end>
				<Aux:instance rdf:nodeID="bnode2071B14B-B3E2-497A-BE80-8F30034A1A8E"/>
			</Aux:InstanceAnnotation>
		</Aux:annotation>
		<Aux:annotation>
			<Aux:InstanceAnnotation rdf:nodeID="bnode62FD6DFF-5A3A-4851-9BFE-5D543BAD8C64">
				<Aux:annotation_start rdf:datatype="http://www.w3.org/2001/XMLSchema#integer">1639</Aux:annotation_start>
				<Aux:annotation_end rdf:datatype="http://www.w3.org/2001/XMLSchema#integer">1642</Aux:annotation_end>
				<Aux:instance rdf:nodeID="bnode9A947B7D-851C-485C-BD73-FB175ECF25CC"/>
			</Aux:InstanceAnnotation>
		</Aux:annotation>
		<Aux:annotation>
			<Aux:InstanceAnnotation rdf:nodeID="bnodeAB906CA9-CC4E-4DDB-8880-A06BA01327D4">
				<Aux:annotation_start rdf:datatype="http://www.w3.org/2001/XMLSchema#integer">1690</Aux:annotation_start>
				<Aux:annotation_end rdf:datatype="http://www.w3.org/2001/XMLSchema#integer">1700</Aux:annotation_end>
				<Aux:instance rdf:nodeID="bnode796B7D55-5DBA-471B-BB96-F23320C70003"/>
			</Aux:InstanceAnnotation>
		</Aux:annotation>
		<Aux:annotation>
			<Aux:InstanceAnnotation rdf:nodeID="bnode02CB28D0-A8D5-4BFD-8CFD-1783AB8AEA57">
				<Aux:annotation_start rdf:datatype="http://www.w3.org/2001/XMLSchema#integer">1737</Aux:annotation_start>
				<Aux:annotation_end rdf:datatype="http://www.w3.org/2001/XMLSchema#integer">1752</Aux:annotation_end>
				<Aux:instance rdf:nodeID="bnodeB94AA13C-8F0C-4AEA-BC9D-15039287EDAC"/>
			</Aux:InstanceAnnotation>
		</Aux:annotation>
		<Aux:annotation>
			<Aux:InstanceAnnotation rdf:nodeID="bnode62152823-A5DB-43D0-AB6E-6DD66E6833CD">
				<Aux:annotation_start rdf:datatype="http://www.w3.org/2001/XMLSchema#integer">1774</Aux:annotation_start>
				<Aux:annotation_end rdf:datatype="http://www.w3.org/2001/XMLSchema#integer">1786</Aux:annotation_end>
				<Aux:instance rdf:nodeID="bnodeE23BC4EF-79EF-4973-BD76-53E531A5C503"/>
			</Aux:InstanceAnnotation>
		</Aux:annotation>
		<Aux:annotation>
			<Aux:InstanceAnnotation rdf:nodeID="bnode2A1EA6FF-C552-4B7B-9E87-5160C24F07AE">
				<Aux:annotation_start rdf:datatype="http://www.w3.org/2001/XMLSchema#integer">1781</Aux:annotation_start>
				<Aux:annotation_end rdf:datatype="http://www.w3.org/2001/XMLSchema#integer">1786</Aux:annotation_end>
				<Aux:instance rdf:nodeID="bnodeB00EDC9B-071F-4112-B168-70F077F04474"/>
			</Aux:InstanceAnnotation>
		</Aux:annotation>
		<Aux:annotation>
			<Aux:InstanceAnnotation rdf:nodeID="bnode1E56E8BC-C3AF-4238-8250-94F03AB8FFEA">
				<Aux:annotation_start rdf:datatype="http://www.w3.org/2001/XMLSchema#integer">1910</Aux:annotation_start>
				<Aux:annotation_end rdf:datatype="http://www.w3.org/2001/XMLSchema#integer">1912</Aux:annotation_end>
				<Aux:instance rdf:nodeID="bnode0F3ED7E7-DBF9-4152-8619-C5E3C3731FBC"/>
			</Aux:InstanceAnnotation>
		</Aux:annotation>
		<Aux:annotation>
			<Aux:InstanceAnnotation rdf:nodeID="bnode445299B3-193F-45C4-9F6B-D67E790A4A3A">
				<Aux:annotation_start rdf:datatype="http://www.w3.org/2001/XMLSchema#integer">1944</Aux:annotation_start>
				<Aux:annotation_end rdf:datatype="http://www.w3.org/2001/XMLSchema#integer">1954</Aux:annotation_end>
				<Aux:instance rdf:nodeID="bnodeBFD76367-390B-4EB1-BBAD-174E317B930D"/>
			</Aux:InstanceAnnotation>
		</Aux:annotation>
		<Aux:annotation>
			<Aux:InstanceAnnotation rdf:nodeID="bnode536C1AAB-D6BE-43DF-A54B-0393A453D3B3">
				<Aux:annotation_start rdf:datatype="http://www.w3.org/2001/XMLSchema#integer">1964</Aux:annotation_start>
				<Aux:annotation_end rdf:datatype="http://www.w3.org/2001/XMLSchema#integer">1966</Aux:annotation_end>
				<Aux:instance rdf:nodeID="bnodeB157B53B-5E70-4E32-9F42-81991F9C56AA"/>
			</Aux:InstanceAnnotation>
		</Aux:annotation>
		<Aux:annotation>
			<Aux:InstanceAnnotation rdf:nodeID="bnodeC0E47FFF-2811-4388-9832-17F05DAF6AA1">
				<Aux:annotation_start rdf:datatype="http://www.w3.org/2001/XMLSchema#integer">2008</Aux:annotation_start>
				<Aux:annotation_end rdf:datatype="http://www.w3.org/2001/XMLSchema#integer">2014</Aux:annotation_end>
				<Aux:instance rdf:nodeID="bnodeE007CBE7-0346-4812-B7C1-9C9F2FC5914C"/>
			</Aux:InstanceAnnotation>
		</Aux:annotation>
		<Aux:annotation>
			<Aux:InstanceAnnotation rdf:nodeID="bnode1FB2018C-2C0F-40EB-A9B9-4DCA306C159C">
				<Aux:annotation_start rdf:datatype="http://www.w3.org/2001/XMLSchema#integer">2023</Aux:annotation_start>
				<Aux:annotation_end rdf:datatype="http://www.w3.org/2001/XMLSchema#integer">2052</Aux:annotation_end>
				<Aux:instance rdf:nodeID="bnodeCC167A94-8101-459B-B099-933EA51669EF"/>
			</Aux:InstanceAnnotation>
		</Aux:annotation>
		<Aux:annotation>
			<Aux:InstanceAnnotation rdf:nodeID="bnode2CC4AAAE-50F6-42D8-9F83-B130F6B43E58">
				<Aux:annotation_start rdf:datatype="http://www.w3.org/2001/XMLSchema#integer">2042</Aux:annotation_start>
				<Aux:annotation_end rdf:datatype="http://www.w3.org/2001/XMLSchema#integer">2052</Aux:annotation_end>
				<Aux:instance rdf:nodeID="bnode5198DCC8-13C8-43AF-ACEB-ACDBE219947A"/>
			</Aux:InstanceAnnotation>
		</Aux:annotation>
		<Aux:annotation>
			<Aux:InstanceAnnotation rdf:nodeID="bnodeFD66A5E5-7D9E-44D6-B660-B813C379EB4D">
				<Aux:annotation_start rdf:datatype="http://www.w3.org/2001/XMLSchema#integer">2055</Aux:annotation_start>
				<Aux:annotation_end rdf:datatype="http://www.w3.org/2001/XMLSchema#integer">2067</Aux:annotation_end>
				<Aux:instance rdf:nodeID="bnode0468F3AE-6E8E-4AD1-A6C7-DF0C9A1BED62"/>
			</Aux:InstanceAnnotation>
		</Aux:annotation>
		<Aux:annotation>
			<Aux:InstanceAnnotation rdf:nodeID="bnode85E0B5F5-37DD-471A-AD82-11B582972690">
				<Aux:annotation_start rdf:datatype="http://www.w3.org/2001/XMLSchema#integer">2062</Aux:annotation_start>
				<Aux:annotation_end rdf:datatype="http://www.w3.org/2001/XMLSchema#integer">2067</Aux:annotation_end>
				<Aux:instance rdf:nodeID="bnode311CE25D-0485-45A7-A9A5-F1E552F9F3AF"/>
			</Aux:InstanceAnnotation>
		</Aux:annotation>
		<Aux:annotation>
			<Aux:InstanceAnnotation rdf:nodeID="bnode67980CAA-79AD-4653-A612-F282B06A269C">
				<Aux:annotation_start rdf:datatype="http://www.w3.org/2001/XMLSchema#integer">2093</Aux:annotation_start>
				<Aux:annotation_end rdf:datatype="http://www.w3.org/2001/XMLSchema#integer">2109</Aux:annotation_end>
				<Aux:instance rdf:nodeID="bnodeD6888080-376A-4332-97C1-D261EDA2A4CB"/>
			</Aux:InstanceAnnotation>
		</Aux:annotation>
		<Aux:annotation>
			<Aux:InstanceAnnotation rdf:nodeID="bnodeB11BF356-194E-4D26-8EF7-0099A2B4135E">
				<Aux:annotation_start rdf:datatype="http://www.w3.org/2001/XMLSchema#integer">2099</Aux:annotation_start>
				<Aux:annotation_end rdf:datatype="http://www.w3.org/2001/XMLSchema#integer">2109</Aux:annotation_end>
				<Aux:instance rdf:nodeID="bnode2735B2C1-6616-49ED-8D8E-64EE9C466FB0"/>
			</Aux:InstanceAnnotation>
		</Aux:annotation>
		<Aux:annotation>
			<Aux:InstanceAnnotation rdf:nodeID="bnode40BBC5C7-742A-405A-A1BF-D245533C147C">
				<Aux:annotation_start rdf:datatype="http://www.w3.org/2001/XMLSchema#integer">2166</Aux:annotation_start>
				<Aux:annotation_end rdf:datatype="http://www.w3.org/2001/XMLSchema#integer">2171</Aux:annotation_end>
				<Aux:instance rdf:nodeID="bnode0E9EFDAE-9A8E-466D-866F-7AB0FDB53B6B"/>
			</Aux:InstanceAnnotation>
		</Aux:annotation>
		<Aux:annotation>
			<Aux:InstanceAnnotation rdf:nodeID="bnode3FE3B38E-C8B1-4CD2-BBBE-A7616C96CFF8">
				<Aux:annotation_start rdf:datatype="http://www.w3.org/2001/XMLSchema#integer">2198</Aux:annotation_start>
				<Aux:annotation_end rdf:datatype="http://www.w3.org/2001/XMLSchema#integer">2200</Aux:annotation_end>
				<Aux:instance rdf:nodeID="bnode7E88EC26-CC6E-4ED8-9804-677F33703875"/>
			</Aux:InstanceAnnotation>
		</Aux:annotation>
		<Aux:annotation>
			<Aux:InstanceAnnotation rdf:nodeID="bnodeA0D1C9AC-5660-4B1F-A469-058AB94A4CBD">
				<Aux:annotation_start rdf:datatype="http://www.w3.org/2001/XMLSchema#integer">2226</Aux:annotation_start>
				<Aux:annotation_end rdf:datatype="http://www.w3.org/2001/XMLSchema#integer">2244</Aux:annotation_end>
				<Aux:instance rdf:nodeID="bnode3E51FCCF-B1D6-4A6C-8276-5DF37022E63D"/>
			</Aux:InstanceAnnotation>
		</Aux:annotation>
		<Aux:annotation>
			<Aux:InstanceAnnotation rdf:nodeID="bnode1D3AB82A-EDD0-4D23-BE22-DF3FBF74BE36">
				<Aux:annotation_start rdf:datatype="http://www.w3.org/2001/XMLSchema#integer">2234</Aux:annotation_start>
				<Aux:annotation_end rdf:datatype="http://www.w3.org/2001/XMLSchema#integer">2244</Aux:annotation_end>
				<Aux:instance rdf:nodeID="bnode2D82EB63-41C4-4449-9F12-0DCAA1B8D438"/>
			</Aux:InstanceAnnotation>
		</Aux:annotation>
		<Aux:annotation>
			<Aux:InstanceAnnotation rdf:nodeID="bnodeF8E66626-43CC-4E08-A4C4-26BAC0655B35">
				<Aux:annotation_start rdf:datatype="http://www.w3.org/2001/XMLSchema#integer">2248</Aux:annotation_start>
				<Aux:annotation_end rdf:datatype="http://www.w3.org/2001/XMLSchema#integer">2254</Aux:annotation_end>
				<Aux:instance rdf:nodeID="bnodeE2368B56-F465-464C-B42C-886CA329AB59"/>
			</Aux:InstanceAnnotation>
		</Aux:annotation>
		<Aux:annotation>
			<Aux:InstanceAnnotation rdf:nodeID="bnode8C6F4785-908A-49D9-8F08-6D976A43ED5D">
				<Aux:annotation_start rdf:datatype="http://www.w3.org/2001/XMLSchema#integer">2257</Aux:annotation_start>
				<Aux:annotation_end rdf:datatype="http://www.w3.org/2001/XMLSchema#integer">2266</Aux:annotation_end>
				<Aux:instance rdf:nodeID="bnode2194FE51-C170-4203-995D-B21C671DC302"/>
			</Aux:InstanceAnnotation>
		</Aux:annotation>
		<Aux:annotation>
			<Aux:InstanceAnnotation rdf:nodeID="bnode8DF529B6-F508-428C-8097-4AB8B36C617D">
				<Aux:annotation_start rdf:datatype="http://www.w3.org/2001/XMLSchema#integer">2270</Aux:annotation_start>
				<Aux:annotation_end rdf:datatype="http://www.w3.org/2001/XMLSchema#integer">2300</Aux:annotation_end>
				<Aux:instance rdf:nodeID="bnodeA09E889E-D93C-450F-83EF-4C79AB2EAC7E"/>
			</Aux:InstanceAnnotation>
		</Aux:annotation>
		<Aux:annotation>
			<Aux:InstanceAnnotation rdf:nodeID="bnode8D40F541-3AA5-4F50-8198-3C94F80963FC">
				<Aux:annotation_start rdf:datatype="http://www.w3.org/2001/XMLSchema#integer">2277</Aux:annotation_start>
				<Aux:annotation_end rdf:datatype="http://www.w3.org/2001/XMLSchema#integer">2300</Aux:annotation_end>
				<Aux:instance rdf:nodeID="bnodeCDC15646-625F-4EA5-BE6E-AD6CF7BE3974"/>
			</Aux:InstanceAnnotation>
		</Aux:annotation>
		<Aux:annotation>
			<Aux:InstanceAnnotation rdf:nodeID="bnodeB9B29D99-E21D-4316-8CE2-F7AE0059E32F">
				<Aux:annotation_start rdf:datatype="http://www.w3.org/2001/XMLSchema#integer">2392</Aux:annotation_start>
				<Aux:annotation_end rdf:datatype="http://www.w3.org/2001/XMLSchema#integer">2401</Aux:annotation_end>
				<Aux:instance rdf:nodeID="bnode09738B4F-ADE4-49C2-BA51-D3A7269BBCEE"/>
			</Aux:InstanceAnnotation>
		</Aux:annotation>
		<Aux:annotation>
			<Aux:InstanceAnnotation rdf:nodeID="bnodeF93B471E-52D2-4FE8-86BC-DC182A4A15B9">
				<Aux:annotation_start rdf:datatype="http://www.w3.org/2001/XMLSchema#integer">2430</Aux:annotation_start>
				<Aux:annotation_end rdf:datatype="http://www.w3.org/2001/XMLSchema#integer">2442</Aux:annotation_end>
				<Aux:instance rdf:nodeID="bnodeBF82A494-7850-4B24-8AA2-620A2169488B"/>
			</Aux:InstanceAnnotation>
		</Aux:annotation>
		<Aux:annotation>
			<Aux:InstanceAnnotation rdf:nodeID="bnode6E101EB3-F2CA-4A47-A2D1-A95EC515115A">
				<Aux:annotation_start rdf:datatype="http://www.w3.org/2001/XMLSchema#integer">2437</Aux:annotation_start>
				<Aux:annotation_end rdf:datatype="http://www.w3.org/2001/XMLSchema#integer">2442</Aux:annotation_end>
				<Aux:instance rdf:nodeID="bnode8013C8C1-0E0B-462B-9093-147872C61CA1"/>
			</Aux:InstanceAnnotation>
		</Aux:annotation>
	</Aux:TextAnnotations>
</rdf:RDF>